CHANGELOG.md
pciw/__init__.py
pciw/__main__.py
pciw/conv.py
pciw/conv.pyi
pciw/data/t_cpu/Windows-x86_64/OpenHardwareMonitorLib.dll
pciw/data/t_cpu/Windows-x86_64/parser.py
pciw/data/t_cpu/Windows-x86_64/t_cpu.exe
pciw/data/t_cpu/Windows-x86_64/t_cpu.exe.config
pciw/LinuxParser.py
pciw/PassParser.py
pciw/pciw.py
pciw/SupportHandler.py
pciw/tree.py
pciw/Types.py
pciw/units.py
pciw/WindowsParser.py
pciw_py-0.9.9.dist-info/LICENSE
pciw_py-0.9.9.dist-info/METADATA
pciw_py-0.9.9.dist-info/WHEEL
pciw_py-0.9.9.dist-info/RECORD
